pyvtt/__init__.py
pyvtt/commands.py
pyvtt/comparablemixin.py
pyvtt/compat.py
pyvtt/version.py
pyvtt/vttexc.py
pyvtt/vttfile.py
pyvtt/vttitem.py
pyvtt/vtttime.py
pyvtt-0.0.4.dist-info/LICENCE.txt
pyvtt-0.0.4.dist-info/METADATA
pyvtt-0.0.4.dist-info/WHEEL
pyvtt-0.0.4.dist-info/entry_points.txt
pyvtt-0.0.4.dist-info/top_level.txt
pyvtt-0.0.4.dist-info/RECORD
